prdc/Dataset.py
prdc/Models.py
prdc/__init__.py
prdc/prdc.py
prdc/prdc_cli.py
prdc/utils.py
prdc_cli-0.0.1.dist-info/LICENSE.md
prdc_cli-0.0.1.dist-info/METADATA
prdc_cli-0.0.1.dist-info/WHEEL
prdc_cli-0.0.1.dist-info/entry_points.txt
prdc_cli-0.0.1.dist-info/top_level.txt
prdc_cli-0.0.1.dist-info/RECORD
