Metadata-Version: 2.1
Name: prdc-cli
Version: 0.0.1
Summary: Compute precision, recall, density, and coverage metrics for custom datasets
Home-page: https://github.com/mahmood-hussain/prdc
Author: NAVER Corp., Mahmood Hussain
Classifier: Programming Language :: Python :: 3
Classifier: License :: OSI Approved :: MIT License
Classifier: Operating System :: OS Independent
License-File: LICENSE.md
Requires-Dist: numpy
Requires-Dist: scikit-learn
Requires-Dist: scipy
Requires-Dist: joblib
Requires-Dist: torch
Requires-Dist: torchvision
Requires-Dist: Pillow
Requires-Dist: tqdm
